employee/__init__.py
employee/admin.py
employee/apps.py
employee/contact_urls.py
employee/context_processors.py
employee/forms.py
employee/models.py
employee/signals.py
employee/tests.py
employee/urls.py
employee/urls_reports.py
employee/utils.py
employee/views.py
employee/api/__init__.py
employee/api/urls.py
employee/api/views.py
employee/api/__pycache__/__init__.cpython-310.pyc
employee/api/__pycache__/__init__.cpython-37.pyc
employee/api/__pycache__/__init__.cpython-39.pyc
employee/api/__pycache__/urls.cpython-310.pyc
employee/api/__pycache__/urls.cpython-37.pyc
employee/api/__pycache__/urls.cpython-39.pyc
employee/api/__pycache__/views.cpython-310.pyc
employee/api/__pycache__/views.cpython-37.pyc
employee/api/__pycache__/views.cpython-39.pyc
employee/migrations/0001_initial.py
employee/migrations/0002_curempposition_curempdivision.py
employee/migrations/0003_employee_is_new.py
employee/migrations/0004_employee_emp_id.py
employee/migrations/0005_alter_employee_blood_alter_employee_father_and_more.py
employee/migrations/0006_fidnumber_bank_address_fidnumber_customer_name_and_more.py
employee/migrations/0007_alter_fidnumber_customer_name.py
employee/migrations/0008_empspecialize.py
employee/migrations/0009_alter_empspecialize_name.py
employee/migrations/0010_formaleducation_year.py
employee/migrations/0011_nonformaleducation_year.py
employee/migrations/0012_auto_20221122_1104.py
employee/migrations/0013_auto_20221122_1127.py
employee/migrations/0014_auto_20221130_2303.py
employee/migrations/0015_auto_20221130_2304.py
employee/migrations/0016_auto_20221130_2326.py
employee/migrations/0017_auto_20221130_2335.py
employee/migrations/0018_employee_pin.py
employee/migrations/0019_employee_ext.py
employee/migrations/0020_auto_20230117_1829.py
employee/migrations/0021_emplanguage_file_language.py
employee/migrations/0022_alter_photo_image.py
employee/migrations/0023_alter_photo_image.py
employee/migrations/0024_alter_fidnumber_options.py
django_ipghrms_employee-1.20.dist-info/LICENSE
django_ipghrms_employee-1.20.dist-info/METADATA
django_ipghrms_employee-1.20.dist-info/WHEEL
django_ipghrms_employee-1.20.dist-info/top_level.txt
django_ipghrms_employee-1.20.dist-info/RECORD
